ishne_to_csv/__init__.py
ishne_to_csv/cli.py
ishne_to_csv/core.py
ishne_to_csv-1.2.dist-info/licenses/LICENSE
ishne_to_csv-1.2.dist-info/METADATA
ishne_to_csv-1.2.dist-info/WHEEL
ishne_to_csv-1.2.dist-info/entry_points.txt
ishne_to_csv-1.2.dist-info/top_level.txt
ishne_to_csv-1.2.dist-info/RECORD
