Metadata-Version: 2.4
Name: ishne_to_csv
Version: 1.2
Summary: Convert ISHNE ECG Holter files to timestamped CSV format
Author: Saurabh Barthwal
Classifier: Programming Language :: Python :: 3
Classifier: License :: OSI Approved :: MIT License
Requires-Python: >=3.6
License-File: LICENSE
Requires-Dist: pandas
Requires-Dist: tqdm
Dynamic: author
Dynamic: classifier
Dynamic: description
Dynamic: description-content-type
Dynamic: license-file
Dynamic: requires-dist
Dynamic: requires-python
Dynamic: summary
